{
  "name": "portable_beacons:workshop_room/chests",
  "fallback": "minecraft:empty",
  "elements": [
    {
      "weight": 4,
      "element": {
        "location": "portable_beacons:workshop_room/chests/normal",
        "processors": "minecraft:empty",
        "projection": "rigid",
        "element_type": "minecraft:single_pool_element"
      }
    },
    {
      "weight": 1,
      "element": {
        "location": "portable_beacons:workshop_room/chests/weapons",
        "processors": "minecraft:empty",
        "projection": "rigid",
        "element_type": "minecraft:single_pool_element"
      }
    }
  ]
}